{
  "@microsoft/generator-sharepoint": {
    "plusBeta": false,
    "isCreatingSolution": true,
    "nodeVersion": "18.18.0",
    "sdksVersions": {},
    "version": "1.21.1",
    "libraryName": "web-studio",
    "libraryId": "5139737a-210f-47a4-b1e8-bcb91fa0d02d",
    "environment": "spo",
    "packageManager": "npm",
    "solutionName": "web-studio",
    "solutionShortDescription": "web-studio description",
    "skipFeatureDeployment": true,
    "isDomainIsolated": false,
    "componentType": "webpart"
  }
}
